differentiable_voronoi/__init__.py
differentiable_voronoi/differentiable_voronoi.py
differentiable_voronoi/main.py
differentiable_voronoi-0.0.5.dist-info/METADATA
differentiable_voronoi-0.0.5.dist-info/WHEEL
differentiable_voronoi-0.0.5.dist-info/top_level.txt
differentiable_voronoi-0.0.5.dist-info/RECORD
