Metadata-Version: 2.4
Name: differentiable-voronoi
Version: 0.0.5
Summary: differentiable Voronoi tessellation
Home-page: https://github.com/SergeiShumilin/differentiable-voronoi
Author: Sergei Shumilin
Author-email: ishumili@gmail.com
Requires-Dist: contourpy==1.2.1
Requires-Dist: cycler==0.12.1
Requires-Dist: filelock==3.14.0
Requires-Dist: fonttools==4.52.1
Requires-Dist: fsspec==2024.5.0
Requires-Dist: importlib_resources==6.4.0
Requires-Dist: Jinja2==3.1.4
Requires-Dist: kiwisolver==1.4.5
Requires-Dist: MarkupSafe==2.1.5
Requires-Dist: matplotlib==3.9.0
Requires-Dist: mpmath==1.3.0
Requires-Dist: networkx==3.2.1
Requires-Dist: packaging==24.0
Requires-Dist: pillow==10.3.0
Requires-Dist: pyparsing==3.1.2
Requires-Dist: python-dateutil==2.9.0.post0
Requires-Dist: shapely==2.0.4
Requires-Dist: six==1.16.0
Requires-Dist: sympy==1.12
Requires-Dist: tqdm==4.66.4
Requires-Dist: trimesh==4.4.0
Requires-Dist: typing_extensions==4.12.0
Requires-Dist: zipp==3.19.0
Dynamic: author
Dynamic: author-email
Dynamic: home-page
Dynamic: requires-dist
Dynamic: summary
